spark_tts_lib-0.2.1.dist-info/METADATA
spark_tts_lib-0.2.1.dist-info/WHEEL
spark_tts_lib-0.2.1.dist-info/entry_points.txt
spark_tts_lib-0.2.1.dist-info/licenses/LICENSE
spark_tts_lib/SparkTTS.py
spark_tts_lib/__init__.py
spark_tts_lib/models/audio_tokenizer.py
spark_tts_lib/models/bicodec.py
spark_tts_lib/modules/blocks/layers.py
spark_tts_lib/modules/blocks/samper.py
spark_tts_lib/modules/blocks/vocos.py
spark_tts_lib/modules/encoder_decoder/feat_decoder.py
spark_tts_lib/modules/encoder_decoder/feat_encoder.py
spark_tts_lib/modules/encoder_decoder/wave_generator.py
spark_tts_lib/modules/fsq/finite_scalar_quantization.py
spark_tts_lib/modules/fsq/residual_fsq.py
spark_tts_lib/modules/speaker/ecapa_tdnn.py
spark_tts_lib/modules/speaker/perceiver_encoder.py
spark_tts_lib/modules/speaker/pooling_layers.py
spark_tts_lib/modules/speaker/speaker_encoder.py
spark_tts_lib/modules/vq/factorized_vector_quantize.py
spark_tts_lib/utils/__init__.py
spark_tts_lib/utils/audio.py
spark_tts_lib/utils/download.py
spark_tts_lib/utils/file.py
spark_tts_lib/utils/parse_options.sh
spark_tts_lib/utils/token_parser.py
spark_tts_lib-0.2.1.dist-info/RECORD
