Metadata-Version: 2.1
Name: spark-tts-lib
Version: 0.2.1
Summary: A Python package for Spark-TTS.
Author-Email: YowFung <yowfung@outlook.com>, yowfung <yowfung@outlook.com>
License: MIT
Classifier: Development Status :: 3 - Alpha
Classifier: Intended Audience :: Developers
Classifier: Programming Language :: Python :: 3
Classifier: Programming Language :: Python :: 3.10
Classifier: Programming Language :: Python :: 3.11
Classifier: Programming Language :: Python :: 3.12
Classifier: Programming Language :: Python :: 3.13
Classifier: License :: OSI Approved :: Apache Software License
Classifier: Operating System :: OS Independent
Classifier: Topic :: Software Development :: Libraries :: Python Modules
Classifier: Topic :: Multimedia :: Sound/Audio :: Speech
Project-URL: Homepage, https://github.com/YowFung/Spark-TTS-Lib
Project-URL: Bug Tracker, https://github.com/YowFung/Spark-TTS-Lib/issues
Project-URL: Documentation, https://github.com/YowFung/Spark-TTS-Lib#readme
Requires-Python: >=3.10
Requires-Dist: einops>=0.8.1
Requires-Dist: einx>=0.3.0
Requires-Dist: numpy>=2.2.3
Requires-Dist: omegaconf>=2.3.0
Requires-Dist: packaging>=24.2
Requires-Dist: safetensors>=0.5.2
Requires-Dist: soundfile>=0.12.1
Requires-Dist: soxr>=0.5.0.post1
Requires-Dist: torch>=2.5.1
Requires-Dist: torchaudio>=2.5.1
Requires-Dist: tqdm>=4.66.5
Requires-Dist: transformers>=4.46.2
Requires-Dist: huggingface-hub>=0.29.3
Requires-Dist: hf-transfer>=0.1.9
Requires-Dist: retrying>=1.3.4
Provides-Extra: dev
Requires-Dist: black>=23.0.0; extra == "dev"
Requires-Dist: isort>=5.0.0; extra == "dev"
Requires-Dist: commitizen>=3.10.0; extra == "dev"
Requires-Dist: pdm-publish>=0.2.1; extra == "dev"
Requires-Dist: pytest>=8.3.5; extra == "dev"
Requires-Dist: pytest-order>=1.0.1; extra == "dev"
Requires-Dist: flake8>=7.0.0; extra == "dev"
